{
  "slug": "remote-software-engineering-team-lead-bloxroute-labs-1093158",
  "id": "1093158",
  "epoch": 1747040402,
  "date": "2025-05-12T09:00:02+00:00",
  "company": "bloXroute Labs",
  "company_logo": "https://remoteok.com/assets/img/jobs/757eef7e6b4d35c4886ac86e4a9e787c1747040403.png",
  "position": "Software Engineering Team Lead",
  "tags": [
    "software",
    "support",
    "testing",
    "growth",
    "code",
    "lead",
    "go",
    "engineering",
    "backend"
  ],
  "logo": "https://remoteok.com/assets/img/jobs/757eef7e6b4d35c4886ac86e4a9e787c1747040403.png",
  "description": "\\n<p></p><p><br></p><b>Responsibilities</b><ul><li>Lead a small team of blockchain core experts focusing on MEV services/mempool transactions for BSC</li><li>Create offerings that leverage the profit validators gain, while creating offerings for searchers</li><li>Develop and implement strategies to optimize performance&nbsp;</li><li>Collaborate with cross-functional teams to support blockchain best solutions&nbsp;</li><li>Provide insight on best practices working with validators and traders in regards to BSC</li><li>Play a pivotal role in increasing productivity, growth and engagement for the team</li><li>Work on special data analysis projects, as needed</li></ul><p><br></p><b>Requirements</b><ul><li>2+ years experience in managing an Engineering team&nbsp;</li><li>At least 5 years of experience with designing, building, testing and implementing highly scalable and distributed backend systems</li><li>3+ years experience in Blockchain in general</li><li>2+ years experience in Blockchain MEV&nbsp;</li><li>Experience with ETH or BSC MEV, including mev-boost and PBS</li><li>Expertise using Go language</li><li>Strong communication and problem solving skills&nbsp;</li><li>Creative, independent, can do attitude, take ownership of overall responsibilities and a great team player</li><li>Ability to read, modify blockchain core code (geth, bor, prysm, ...)</li></ul><p><br></p><p></p>\\n<br/><br/>Please mention the word **ECENOMICAL** and tag RMzguNjguMTM0LjE5NA== when applying to show you read the job post completely (#RMzguNjguMTM0LjE5NA==). This is a beta feature to avoid spam applicants. Companies can search these words to find applicants that read this and see they're human.",
  "location": "Remote",
  "salary_min": 75000,
  "salary_max": 102500,
  "apply_url": "https://remoteOK.com/remote-jobs/remote-software-engineering-team-lead-bloxroute-labs-1093158",
  "url": "https://remoteOK.com/remote-jobs/remote-software-engineering-team-lead-bloxroute-labs-1093158"
}